peccary/HCplots.py
peccary/__init__.py
peccary/core.py
peccary/examples.py
peccary/timeseries.py
peccary/utils.py
peccary/__pycache__/Cmaxmin.cpython-37.pyc
peccary/__pycache__/PESCy_functions.cpython-37.pyc
peccary/__pycache__/PESCy_functions.cpython-39.pyc
peccary/__pycache__/__init__.cpython-37.pyc
peccary/__pycache__/calcCofH.cpython-37.pyc
peccary/__pycache__/calcH.cpython-37.pyc
peccary/__pycache__/calcH_fromPatternCount.cpython-37.pyc
peccary/__pycache__/calcPESCcurves.cpython-37.pyc
peccary/__pycache__/calcS_fromPatternCount.cpython-37.pyc
peccary/__pycache__/timeseries.cpython-37.pyc
peccary-0.1.1.dist-info/LICENSE
peccary-0.1.1.dist-info/METADATA
peccary-0.1.1.dist-info/WHEEL
peccary-0.1.1.dist-info/top_level.txt
peccary-0.1.1.dist-info/RECORD
