Metadata-Version: 2.1
Name: peccary
Version: 0.1.1
Summary: Package for identifying regular, complex, and stochastic behavior in timeseries
Author-email: Sóley Hyman <soleyhyman@arizona.edu>
Maintainer-email: Sóley Hyman <soleyhyman@arizona.edu>
License: MIT License
Project-URL: Documentation, https://peccary.readthedocs.io/
Project-URL: Repository, https://github.com/soleyhyman/peccary
Project-URL: Issues, https://github.com/soleyhyman/peccary/issues
Keywords: astrophysics,dynamics,physics,plasma,plasma physics,science,chaos,permutation,entropy,statistical,complexity,peccary
Classifier: Development Status :: 4 - Beta
Classifier: Intended Audience :: Science/Research
Classifier: License :: OSI Approved :: MIT License
Classifier: Natural Language :: English
Classifier: Operating System :: OS Independent
Classifier: Operating System :: MacOS
Classifier: Operating System :: Microsoft :: Windows
Classifier: Operating System :: POSIX :: Linux
Classifier: Programming Language :: Python :: 3
Classifier: Programming Language :: Python :: 3.8
Classifier: Programming Language :: Python :: 3.9
Classifier: Programming Language :: Python :: 3.10
Classifier: Programming Language :: Python :: 3.11
Classifier: Programming Language :: Python :: 3.12
Classifier: Topic :: Scientific/Engineering :: Astronomy
Classifier: Topic :: Scientific/Engineering :: Physics
Classifier: Topic :: Software Development :: Libraries :: Python Modules
Requires-Python: >=3.8
License-File: LICENSE
Requires-Dist: numpy >=1.14
Requires-Dist: scipy >=0.19
Requires-Dist: matplotlib
